benchmark_llm_serving/__init__.py
benchmark_llm_serving/backends.py
benchmark_llm_serving/bench_suite.py
benchmark_llm_serving/benchmark.py
benchmark_llm_serving/io_classes.py
benchmark_llm_serving/make_graphs.py
benchmark_llm_serving/make_readmes.py
benchmark_llm_serving/utils.py
benchmark_llm_serving/utils_args.py
benchmark_llm_serving/utils_metrics.py
benchmark_llm_serving/datasets/growing_prompts.json
benchmark_llm_serving/datasets/prompts_length_1024.json
benchmark_llm_serving/datasets/prompts_length_128.json
benchmark_llm_serving/datasets/prompts_length_2048.json
benchmark_llm_serving/datasets/prompts_length_256.json
benchmark_llm_serving/datasets/prompts_length_32.json
benchmark_llm_serving/datasets/prompts_length_4096.json
benchmark_llm_serving/datasets/prompts_length_512.json
benchmark_llm_serving/query_profiles/__init__.py
benchmark_llm_serving/query_profiles/constant_number.py
benchmark_llm_serving/query_profiles/growing_requests.py
benchmark_llm_serving/query_profiles/query_functions.py
benchmark_llm_serving/query_profiles/scheduled_requests.py
benchmark_llm_serving-1.0.3.dist-info/LICENSE
benchmark_llm_serving-1.0.3.dist-info/METADATA
benchmark_llm_serving-1.0.3.dist-info/WHEEL
benchmark_llm_serving-1.0.3.dist-info/entry_points.txt
benchmark_llm_serving-1.0.3.dist-info/top_level.txt
benchmark_llm_serving-1.0.3.dist-info/RECORD
