Metadata-Version: 2.1
Name: benchmark_llm_serving
Version: 1.0.3
Summary: A library to benchmark LLMs via their API exposure
Author: Agence Data Services FT
Author-email: drosdadssocle.00620@francetravail.fr
License: GNU AFFERO GENERAL PUBLIC LICENSE
Project-URL: Repository, https://github.com/France-Travail/benchmark_llm_serving
Classifier: Programming Language :: Python :: 3
Classifier: Programming Language :: Python :: 3.10
Classifier: Programming Language :: Python :: 3.11
Requires-Python: <4.0,>=3.10
License-File: LICENSE
Requires-Dist: aiohttp <4.0,>=3.9.5
Requires-Dist: prometheus-client <1.0,>=0.20.0
Requires-Dist: matplotlib <4.0,>=3.9.1
Requires-Dist: pydantic <3.0,>=2.8.2
Requires-Dist: pydantic-settings <3.0,>=2.3.4
Requires-Dist: requests <3.0,>=2.32.3
Requires-Dist: mdutils <2.0,>=1.6.0
Provides-Extra: test
Requires-Dist: httpx <1.0,>=0.27 ; extra == 'test'
Requires-Dist: pytest <9.0,>=8.3.2 ; extra == 'test'
Requires-Dist: pytest-cov <6.0,>=5.0.0 ; extra == 'test'
Requires-Dist: mypy <2.0,>=1.11.0 ; extra == 'test'
Requires-Dist: pytest-asyncio <1.0,>=0.23.8 ; extra == 'test'
Requires-Dist: aioresponses <1.0,>=0.7.6 ; extra == 'test'
Requires-Dist: requests-mock <2.0,>=1.12.1 ; extra == 'test'
